[
  {
    "title": "How do you serve your community?",
    "description": ,
    "image": {
      "url": "images/features/grouppeople",
      "width": 80,
      "height": 80
    }
  },
  {
    "title": "Do you know your neighbors?",
    "description": ,
    "image": {
      "url": "images/features/handgesture",
      "width": 80,
      "height": 80
    }
  },
  {
    "title": "How does your community serve you?",
    "description": ,
    "image": {
      "url": "images/features/twopeople",
      "width": 80,
      "height": 80
    }
  }
]
